opensimula/Child.py
opensimula/Component.py
opensimula/Iterative_process.py
opensimula/Message.py
opensimula/Parameter_container.py
opensimula/Parameters.py
opensimula/Project.py
opensimula/Simulation.py
opensimula/Variable.py
opensimula/__init__.py
opensimula/components/Building.py
opensimula/components/Building_surface.py
opensimula/components/Calculator.py
opensimula/components/Construction.py
opensimula/components/Day_schedule.py
opensimula/components/File_data.py
opensimula/components/File_met.py
opensimula/components/Frame.py
opensimula/components/Glazing.py
opensimula/components/HVAC_DX_equipment.py
opensimula/components/HVAC_DX_system.py
opensimula/components/HVAC_MZW_system.py
opensimula/components/HVAC_SZW_system.py
opensimula/components/HVAC_coil_equipment.py
opensimula/components/HVAC_fan_equipment.py
opensimula/components/HVAC_perfect_system.py
opensimula/components/Material.py
opensimula/components/Opening.py
opensimula/components/Opening_type.py
opensimula/components/Solar_surface.py
opensimula/components/Space.py
opensimula/components/Space_type.py
opensimula/components/Surface.py
opensimula/components/Test_component.py
opensimula/components/Week_schedule.py
opensimula/components/Year_schedule.py
opensimula/components/__init__.py
opensimula/visual_3D/Environment_3D.py
opensimula/visual_3D/Polygon_3D.py
opensimula-0.5.2.dist-info/licenses/LICENSE
opensimula-0.5.2.dist-info/METADATA
opensimula-0.5.2.dist-info/WHEEL
opensimula-0.5.2.dist-info/top_level.txt
opensimula-0.5.2.dist-info/RECORD
